{"date": "2026-03-08", "entries": {"2026-03-08|KXLOWTMIA-26MAR08-T72|BUY NO": {"count": 1, "last_edge_pct": 39.4, "last_post_ts_epoch": 1772946000.001004, "last_post_ts_est": "2026-03-08 12:00:00 AM EST", "city": "Miami", "temp_side": "low"}, "2026-03-08|KXHIGHMIA-26MAR08-B84.5|BUY NO": {"count": 1, "last_edge_pct": 18.86, "last_post_ts_epoch": 1772946000.001004, "last_post_ts_est": "2026-03-08 12:00:00 AM EST", "city": "Miami", "temp_side": "high"}, "2026-03-08|KXHIGHTBOS-26MAR08-T58|BUY NO": {"count": 1, "last_edge_pct": 9.4, "last_post_ts_epoch": 1772946000.001004, "last_post_ts_est": "2026-03-08 12:00:00 AM EST", "city": "Boston", "temp_side": "high"}, "2026-03-08|KXHIGHNY-26MAR08-B64.5|BUY NO": {"count": 1, "last_edge_pct": 7.18, "last_post_ts_epoch": 1772946180.00053, "last_post_ts_est": "2026-03-08 12:03:00 AM EST", "city": "New York City", "temp_side": "high"}, "2026-03-08|KXHIGHTBOS-26MAR08-T58|BUY YES": {"count": 1, "last_edge_pct": 13.79, "last_post_ts_epoch": 1772946420.000089, "last_post_ts_est": "2026-03-08 12:07:00 AM EST", "city": "Boston", "temp_side": "high"}, "2026-03-08|KXHIGHPHIL-26MAR08-B69.5|BUY NO": {"count": 1, "last_edge_pct": 33.0, "last_post_ts_epoch": 1772946840.000586, "last_post_ts_est": "2026-03-08 12:14:00 AM EST", "city": "Philadelphia", "temp_side": "high"}, "2026-03-08|KXHIGHTBOS-26MAR08-B58.5|BUY NO": {"count": 1, "last_edge_pct": 23.0, "last_post_ts_epoch": 1772947020.000298, "last_post_ts_est": "2026-03-08 12:17:00 AM EST", "city": "Boston", "temp_side": "high"}, "2026-03-08|KXLOWTPHIL-26MAR08-T47|BUY YES": {"count": 1, "last_edge_pct": 61.79, "last_post_ts_epoch": 1772947440.000314, "last_post_ts_est": "2026-03-08 12:24:00 AM EST", "city": "Philadelphia", "temp_side": "low"}, "2026-03-08|KXHIGHTATL-26MAR08-B73.5|BUY NO": {"count": 1, "last_edge_pct": 14.0, "last_post_ts_epoch": 1772947680.001432, "last_post_ts_est": "2026-03-08 12:28:00 AM EST", "city": "Atlanta", "temp_side": "high"}, "2026-03-08|KXHIGHTDC-26MAR08-B70.5|BUY NO": {"count": 1, "last_edge_pct": 8.37, "last_post_ts_epoch": 1772948520.001371, "last_post_ts_est": "2026-03-08 12:42:00 AM EST", "city": "Washington DC", "temp_side": "high"}, "2026-03-08|KXHIGHTDAL-26MAR08-B72.5|BUY NO": {"count": 1, "last_edge_pct": 32.0, "last_post_ts_epoch": 1772949720.001541, "last_post_ts_est": "2026-03-08 01:02:00 AM EST", "city": "Dallas", "temp_side": "high"}, "2026-03-08|KXLOWTCHI-26MAR08-B34.5|BUY NO": {"count": 1, "last_edge_pct": 27.0, "last_post_ts_epoch": 1772949720.001541, "last_post_ts_est": "2026-03-08 01:02:00 AM EST", "city": "Chicago", "temp_side": "low"}, "2026-03-08|KXHIGHTHOU-26MAR08-B75.5|BUY NO": {"count": 1, "last_edge_pct": 25.0, "last_post_ts_epoch": 1772949720.001541, "last_post_ts_est": "2026-03-08 01:02:00 AM EST", "city": "Houston", "temp_side": "high"}, "2026-03-08|KXHIGHTSATX-26MAR08-B70.5|BUY NO": {"count": 1, "last_edge_pct": 19.0, "last_post_ts_epoch": 1772949960.001339, "last_post_ts_est": "2026-03-08 01:06:00 AM EST", "city": "San Antonio", "temp_side": "high"}, "2026-03-08|KXHIGHTNOLA-26MAR08-B80.5|BUY NO": {"count": 1, "last_edge_pct": 14.36, "last_post_ts_epoch": 1772949960.001339, "last_post_ts_est": "2026-03-08 01:06:00 AM EST", "city": "New Orleans", "temp_side": "high"}, "2026-03-08|KXHIGHCHI-26MAR08-B63.5|BUY NO": {"count": 1, "last_edge_pct": 19.0, "last_post_ts_epoch": 1772950440.000445, "last_post_ts_est": "2026-03-08 01:14:00 AM EST", "city": "Chicago", "temp_side": "high"}, "2026-03-08|KXHIGHNY-26MAR08-B66.5|BUY NO": {"count": 1, "last_edge_pct": 25.0, "last_post_ts_epoch": 1772950620.000218, "last_post_ts_est": "2026-03-08 01:17:00 AM EST", "city": "New York City", "temp_side": "high"}, "2026-03-08|KXHIGHAUS-26MAR08-B69.5|BUY NO": {"count": 1, "last_edge_pct": 22.0, "last_post_ts_epoch": 1772951040.001323, "last_post_ts_est": "2026-03-08 01:24:00 AM EST", "city": "Austin", "temp_side": "high"}, "2026-03-08|KXLOWTAUS-26MAR08-B53.5|BUY NO": {"count": 1, "last_edge_pct": 20.44, "last_post_ts_epoch": 1772951040.001323, "last_post_ts_est": "2026-03-08 01:24:00 AM EST", "city": "Austin", "temp_side": "low"}, "2026-03-08|KXHIGHTSATX-26MAR08-B68.5|BUY NO": {"count": 1, "last_edge_pct": 34.0, "last_post_ts_epoch": 1772953020.000855, "last_post_ts_est": "2026-03-08 01:57:00 AM EST", "city": "San Antonio", "temp_side": "high"}, "2026-03-08|KXHIGHDEN-26MAR08-T65|BUY NO": {"count": 1, "last_edge_pct": 39.0, "last_post_ts_epoch": 1772953380.000765, "last_post_ts_est": "2026-03-08 02:03:00 AM EST", "city": "Denver", "temp_side": "high"}, "2026-03-08|KXLOWTPHIL-26MAR08-B49.5|BUY NO": {"count": 1, "last_edge_pct": 37.0, "last_post_ts_epoch": 1772953560.001739, "last_post_ts_est": "2026-03-08 02:06:00 AM EST", "city": "Philadelphia", "temp_side": "low"}, "2026-03-08|KXLOWTNYC-26MAR08-B51.5|BUY NO": {"count": 1, "last_edge_pct": 49.0, "last_post_ts_epoch": 1772954640.000931, "last_post_ts_est": "2026-03-08 02:24:00 AM EST", "city": "New York City", "temp_side": "low"}, "2026-03-08|KXLOWTDEN-26MAR08-T32|BUY YES": {"count": 1, "last_edge_pct": 8.46, "last_post_ts_epoch": 1772955300.00049, "last_post_ts_est": "2026-03-08 02:35:00 AM EST", "city": "Denver", "temp_side": "low"}, "2026-03-08|KXHIGHTPHX-26MAR08-B90.5|BUY NO": {"count": 1, "last_edge_pct": 29.0, "last_post_ts_epoch": 1772955480.000552, "last_post_ts_est": "2026-03-08 02:38:00 AM EST", "city": "Phoenix", "temp_side": "high"}, "2026-03-08|KXHIGHTMIN-26MAR08-T61|BUY NO": {"count": 1, "last_edge_pct": 31.99, "last_post_ts_epoch": 1772956740.000636, "last_post_ts_est": "2026-03-08 02:59:00 AM EST", "city": "Minneapolis", "temp_side": "high"}, "2026-03-08|KXHIGHTSFO-26MAR08-B72.5|BUY NO": {"count": 1, "last_edge_pct": 31.0, "last_post_ts_epoch": 1772957040.000881, "last_post_ts_est": "2026-03-08 03:04:00 AM EST", "city": "San Francisco", "temp_side": "high"}, "2026-03-08|KXHIGHLAX-26MAR08-B86.5|BUY NO": {"count": 1, "last_edge_pct": 39.0, "last_post_ts_epoch": 1772957220.000952, "last_post_ts_est": "2026-03-08 03:07:00 AM EST", "city": "Los Angeles", "temp_side": "high"}, "2026-03-08|KXLOWTNYC-26MAR08-B49.5|BUY NO": {"count": 1, "last_edge_pct": 45.81, "last_post_ts_epoch": 1772957580.000871, "last_post_ts_est": "2026-03-08 03:13:00 AM EST", "city": "New York City", "temp_side": "low"}, "2026-03-08|KXLOWTCHI-26MAR08-B32.5|BUY NO": {"count": 1, "last_edge_pct": 63.0, "last_post_ts_epoch": 1772957760.001154, "last_post_ts_est": "2026-03-08 03:16:00 AM EST", "city": "Chicago", "temp_side": "low"}, "2026-03-08|KXHIGHTSEA-26MAR08-B52.5|BUY NO": {"count": 1, "last_edge_pct": 50.0, "last_post_ts_epoch": 1772959500.000668, "last_post_ts_est": "2026-03-08 03:45:00 AM EST", "city": "Seattle", "temp_side": "high"}, "2026-03-08|KXHIGHTSEA-26MAR08-B50.5|BUY NO": {"count": 1, "last_edge_pct": 42.0, "last_post_ts_epoch": 1772963880.000415, "last_post_ts_est": "2026-03-08 04:58:00 AM EST", "city": "Seattle", "temp_side": "high"}, "2026-03-08|KXHIGHTLV-26MAR08-B74.5|BUY NO": {"count": 1, "last_edge_pct": 22.02, "last_post_ts_epoch": 1772968620.000617, "last_post_ts_est": "2026-03-08 06:17:00 AM EST", "city": "Las Vegas", "temp_side": "high"}, "2026-03-08|KXHIGHPHIL-26MAR08-B71.5|BUY NO": {"count": 1, "last_edge_pct": 10.0, "last_post_ts_epoch": 1772968620.000617, "last_post_ts_est": "2026-03-08 06:17:00 AM EST", "city": "Philadelphia", "temp_side": "high"}, "2026-03-08|KXLOWTNYC-26MAR08-T45|BUY NO": {"count": 1, "last_edge_pct": 41.21, "last_post_ts_epoch": 1772970840.000731, "last_post_ts_est": "2026-03-08 06:54:00 AM EST", "city": "New York City", "temp_side": "low"}, "2026-03-08|KXHIGHTDC-26MAR08-B74.5|BUY NO": {"count": 1, "last_edge_pct": 34.0, "last_post_ts_epoch": 1772972640.001325, "last_post_ts_est": "2026-03-08 07:24:00 AM EST", "city": "Washington DC", "temp_side": "high"}, "2026-03-08|KXHIGHTOKC-26MAR08-B74.5|BUY NO": {"count": 1, "last_edge_pct": 37.0, "last_post_ts_epoch": 1772976295.093788, "last_post_ts_est": "2026-03-08 08:24:55 AM EST", "city": "Oklahoma City", "temp_side": "high"}, "2026-03-08|KXHIGHLAX-26MAR08-B88.5|BUY NO": {"count": 1, "last_edge_pct": 31.0, "last_post_ts_epoch": 1772977905.855303, "last_post_ts_est": "2026-03-08 08:51:45 AM EST", "city": "Los Angeles", "temp_side": "high"}, "2026-03-08|KXHIGHTSEA-26MAR08-B54.5|BUY NO": {"count": 1, "last_edge_pct": 24.0, "last_post_ts_epoch": 1772979420.000605, "last_post_ts_est": "2026-03-08 09:17:00 AM EST", "city": "Seattle", "temp_side": "high"}, "2026-03-08|KXHIGHTATL-26MAR08-B69.5|BUY NO": {"count": 1, "last_edge_pct": 24.37, "last_post_ts_epoch": 1772985720.000334, "last_post_ts_est": "2026-03-08 11:02:00 AM EST", "city": "Atlanta", "temp_side": "high"}, "2026-03-08|KXHIGHTLV-26MAR08-B76.5|BUY NO": {"count": 1, "last_edge_pct": 22.0, "last_post_ts_epoch": 1772987659.05725, "last_post_ts_est": "2026-03-08 11:34:19 AM EST", "city": "Las Vegas", "temp_side": "high"}, "2026-03-08|KXHIGHTNOLA-26MAR08-B76.5|BUY NO": {"count": 1, "last_edge_pct": 26.0, "last_post_ts_epoch": 1772992680.001324, "last_post_ts_est": "2026-03-08 12:58:00 PM EST", "city": "New Orleans", "temp_side": "high"}, "2026-03-08|KXHIGHTDAL-26MAR08-B74.5|BUY NO": {"count": 1, "last_edge_pct": 24.0, "last_post_ts_epoch": 1772994780.000694, "last_post_ts_est": "2026-03-08 01:33:00 PM EST", "city": "Dallas", "temp_side": "high"}, "2026-03-08|KXHIGHTSFO-26MAR08-B68.5|BUY NO": {"count": 1, "last_edge_pct": 7.9, "last_post_ts_epoch": 1772994780.000694, "last_post_ts_est": "2026-03-08 01:33:00 PM EST", "city": "San Francisco", "temp_side": "high"}}}